LICENSE
MANIFEST.in
readme.md
setup.py
bin/ielu
ielu/__init__.py
ielu/batch.py
ielu/color_utils.py
ielu/custom_list_editor.py
ielu/electrode.py
ielu/electrode_group.py
ielu/file_dialog.py
ielu/geometry.py
ielu/grid.py
ielu/gselu.py
ielu/main.py
ielu/make_dural_surface.csh
ielu/mkoutersurf.py
ielu/name_holder.py
ielu/panel2d.py
ielu/pipeline.py
ielu/plotting_utils.py
ielu/utils.py
ielu.egg-info/PKG-INFO
ielu.egg-info/SOURCES.txt
ielu.egg-info/dependency_links.txt
ielu.egg-info/requires.txt
ielu.egg-info/top_level.txt