Metadata-Version: 2.1
Name: ielu
Version: 0.3.0
Summary: Interactive Electrode localization Utility
Home-page: https://github.com/aestrivex/ielu
Maintainer: Roan LaPlante
Maintainer-email: rlaplant@nmr.mgh.harvard.edu
License: Visuddhimagga Sutta; GPLv3+
Platform: any
Classifier: Development Status :: 4 - Beta
Classifier: Environment :: X11 Applications
Classifier: Intended Audience :: Science/Research
Classifier: License :: OSI Approved :: GNU General Public License v3 or later (GPLv3+)
Classifier: Natural Language :: English
Classifier: Programming Language :: Python :: 3.8
Classifier: Topic :: Scientific/Engineering :: Information Analysis
License-File: LICENSE
